memgen/__init__.py
memgen/__main__.py
memgen/box_shape.py
memgen/defaults.py
memgen/file_types.py
memgen/force_fields.py
memgen/local_memgen.py
memgen/memgen.py
memgen/parse_cli.py
memgen/structure_sources.py
memgen/test_memgen.py
memgen/test_parse_cli.py
memgen-0.0.1b3.dist-info/METADATA
memgen-0.0.1b3.dist-info/WHEEL
memgen-0.0.1b3.dist-info/entry_points.txt
memgen-0.0.1b3.dist-info/top_level.txt
memgen-0.0.1b3.dist-info/RECORD
