Metadata-Version: 2.1
Name: memgen
Version: 0.0.1b3
Summary: Calls MemGen service located at http://memgen.uni-saarland.de/api
Home-page: https://gitlab.com/cbjh/memgen/py-memgen
Author: Maciej Wójcik
Author-email: w8jcik@gmail.com
Classifier: Operating System :: POSIX :: Linux
Requires-Python: >=3.6
Requires-Dist: numpy
Provides-Extra: dev
Requires-Dist: mdanalysis ; extra == 'dev'
Requires-Dist: pytest ; extra == 'dev'
Provides-Extra: external
Requires-Dist: gmxapi ; extra == 'external'
Requires-Dist: openbabel ; extra == 'external'
Provides-Extra: local
Requires-Dist: acpype (~=2022.6.6) ; extra == 'local'
